[
  {
    "date": "2025-10-01",
    "rating": 80.04
  },
  {
    "date": "2025-10-08",
    "rating": 78.86
  },
  {
    "date": "2025-10-15",
    "rating": 81.21
  },
  {
    "date": "2025-10-22",
    "rating": 81.86
  },
  {
    "date": "2025-10-29",
    "rating": 81.73,
    "stateRank": 21,
    "nationalRank": 487
  },
  {
    "date": "2025-11-05",
    "rating": 82.21,
    "stateRank": 21,
    "nationalRank": 471
  },
  {
    "date": "2025-11-12",
    "rating": 82.25,
    "stateRank": 20,
    "nationalRank": 470
  }
]
